arsenalqa/__init__.py
arsenalqa/fields.py
arsenalqa/models.py
arsenalqa/base/__init__.py
arsenalqa/base/exceptions.py
arsenalqa/base/fields.py
arsenalqa/base/iterables.py
arsenalqa/base/transports.py
arsenalqa/base/utils.py
arsenalqa/transports/__init__.py
arsenalqa/transports/managers.py
arsenalqa-2020.0.6.dist-info/LICENSE
arsenalqa-2020.0.6.dist-info/METADATA
arsenalqa-2020.0.6.dist-info/WHEEL
arsenalqa-2020.0.6.dist-info/top_level.txt
arsenalqa-2020.0.6.dist-info/RECORD
